PyWindows/PyWindows.py
PyWindows/__init__.py
PyWindows/lib/C-Python-Window-Lib.dll
PyWindows/lib/SDL2.dll
PyWindows/lib/SDL2_image.dll
PyWindows/lib/player.png
PyWindows-1.0.dist-info/METADATA
PyWindows-1.0.dist-info/WHEEL
PyWindows-1.0.dist-info/top_level.txt
PyWindows-1.0.dist-info/RECORD
