Metadata-Version: 2.1
Name: PyWindows
Version: 1.0
Summary: Windows for Python
Author: Phoneguytech
Classifier: Programming Language :: Python :: 3
Classifier: License :: OSI Approved :: MIT License
Classifier: Operating System :: OS Independent
